odoo/addons/cooperator/README.rst
odoo/addons/cooperator/__init__.py
odoo/addons/cooperator/__manifest__.py
odoo/addons/cooperator/data/data.xml
odoo/addons/cooperator/data/mail_template_data.xml
odoo/addons/cooperator/demo/coop.xml
odoo/addons/cooperator/demo/users.xml
odoo/addons/cooperator/i18n/ca_ES.po
odoo/addons/cooperator/i18n/cooperator.pot
odoo/addons/cooperator/i18n/es.po
odoo/addons/cooperator/i18n/fr.po
odoo/addons/cooperator/i18n/fr_BE.po
odoo/addons/cooperator/i18n/nl_BE.po
odoo/addons/cooperator/migrations/14.0.1.1.0/post-fix_subscription_request_names.py
odoo/addons/cooperator/migrations/14.0.1.1.0/post-remove_subscription_request_subscription_type.py
odoo/addons/cooperator/migrations/14.0.1.7.0/post-set_subscription_journal_on_company.py
odoo/addons/cooperator/migrations/14.0.1.7.0/pre-migration.py
odoo/addons/cooperator/migrations/14.0.2.0.0/post-create_cooperative_memberships.py
odoo/addons/cooperator/models/__init__.py
odoo/addons/cooperator/models/account_chart_template.py
odoo/addons/cooperator/models/account_journal.py
odoo/addons/cooperator/models/account_move.py
odoo/addons/cooperator/models/company.py
odoo/addons/cooperator/models/cooperative_membership.py
odoo/addons/cooperator/models/mail_template.py
odoo/addons/cooperator/models/operation_request.py
odoo/addons/cooperator/models/partner.py
odoo/addons/cooperator/models/product.py
odoo/addons/cooperator/models/share_line.py
odoo/addons/cooperator/models/share_type.py
odoo/addons/cooperator/models/subscription_register.py
odoo/addons/cooperator/models/subscription_request.py
odoo/addons/cooperator/readme/CONTRIBUTORS.rst
odoo/addons/cooperator/readme/DESCRIPTION.rst
odoo/addons/cooperator/readme/HISTORY.rst
odoo/addons/cooperator/readme/INSTALL.rst
odoo/addons/cooperator/readme/ROADMAP.rst
odoo/addons/cooperator/readme/USAGE.rst
odoo/addons/cooperator/report/__init__.py
odoo/addons/cooperator/report/account_invoice_report.py
odoo/addons/cooperator/report/cooperator_certificat_G001.xml
odoo14_addon_cooperator-14.0.3.0.0.dist-info/METADATA
odoo14_addon_cooperator-14.0.3.0.0.dist-info/WHEEL
odoo14_addon_cooperator-14.0.3.0.0.dist-info/top_level.txt
odoo14_addon_cooperator-14.0.3.0.0.dist-info/RECORD
