Metadata-Version: 2.1
Name: odoo14-addon-cooperator
Version: 14.0.3.0.0
Summary: Manage your cooperators
Home-page: https://github.com/OCA/cooperative
Author: Coop IT Easy SC, Odoo Community Association (OCA)
Author-email: support@odoo-community.org
License: AGPL-3
Platform: UNKNOWN
Classifier: Programming Language :: Python
Classifier: Framework :: Odoo
Classifier: Framework :: Odoo :: 14.0
Classifier: License :: OSI Approved :: GNU Affero General Public License v3
Requires-Python: >=3.6
Requires-Dist: odoo14-addon-partner-contact-birthdate
Requires-Dist: odoo14-addon-partner-contact-gender
Requires-Dist: odoo14-addon-partner-firstname
Requires-Dist: odoo (<14.1dev,>=14.0a)
